{"_id":"@oclif/linewrap","_rev":"7-3aab0cb3cd54696c8b72aba79285ee1b","name":"@oclif/linewrap","dist-tags":{"latest":"1.0.0"},"versions":{"1.0.0":{"name":"@oclif/linewrap","version":"1.0.0","description":"","main":"linewrap.js","scripts":{"test":"echo \"Error: no test specified\" && exit 1"},"repository":{"type":"git","url":"git+https://github.com/heroku/node-linewrap.git"},"author":{"name":"Jeff Dickey"},"license":"ISC","bugs":{"url":"https://github.com/heroku/node-linewrap/issues"},"homepage":"https://github.com/heroku/node-linewrap#readme","gitHead":"1d814d79da44b9d513b6caa45e70fc7a948673d7","_id":"@oclif/linewrap@1.0.0","_npmVersion":"5.6.0","_nodeVersion":"9.11.1","_npmUser":{"name":"dickeyxxx","email":"dickeytk+npm@gmail.com"},"dist":{"integrity":"sha512-Ups2dShK52xXa8w6iBWLgcjPJWjais6KPJQq3gQ/88AY6BXoTX+MIGFPrWQO1KLMiQfoTpcLnUwloN4brrVUHw==","shasum":"aedcb64b479d4db7be24196384897b5000901d91","tarball":"https://registry.npmjs.org/@oclif/linewrap/-/linewrap-1.0.0.tgz","fileCount":3,"unpackedSize":27172},"maintainers":[{"name":"dickeyxxx","email":"dickeytk+npm@gmail.com"},{"name":"oclif-bot","email":"jdxcode+oclif@gmail.com"}],"directories":{},"_npmOperationalInternal":{"host":"s3://npm-registry-packages","tmp":"tmp/linewrap_1.0.0_1523245897145_0.7577122342317579"},"_hasShrinkwrap":false}},"time":{"created":"2018-04-09T03:51:37.093Z","1.0.0":"2018-04-09T03:51:37.198Z","modified":"2020-04-14T21:26:09.593Z"},"maintainers":[{"email":"chadcarbert@me.com","name":"chadian"},{"email":"nsamsami@salesforce.com","name":"nsamsami"},{"email":"amphro@gmail.com","name":"amphro"},{"email":"robert.bergman@gmail.com","name":"rbergman"},{"email":"longoria.public@gmail.com","name":"elbandito"},{"email":"philipe.navarro@salesforce.com","name":"rasphilco"},{"email":"npm@jdxcode.com","name":"dickeyxxx"},{"email":"jdxcode+oclif@gmail.com","name":"oclif-bot"}],"homepage":"https://github.com/heroku/node-linewrap#readme","repository":{"type":"git","url":"git+https://github.com/heroku/node-linewrap.git"},"author":{"name":"Jeff Dickey"},"bugs":{"url":"https://github.com/heroku/node-linewrap/issues"},"license":"ISC","readme":"ERROR: No README data found!","readmeFilename":"","_etag":"W/\"be010ee9ceeed0d1a2da200fa0fd194d\"","_lastModified":"Tue, 14 Apr 2020 21:26:10 GMT"}